oh_my_ralph/__init__.py
oh_my_ralph/agent.md
oh_my_ralph/ascii_art.txt
oh_my_ralph/fix_plan.md
oh_my_ralph/prompt.md
oh_my_ralph/ralph_cli.py
oh_my_ralph/ralph_loop.py
oh_my_ralph-0.4.0.dist-info/licenses/LICENSE
oh_my_ralph-0.4.0.dist-info/METADATA
oh_my_ralph-0.4.0.dist-info/WHEEL
oh_my_ralph-0.4.0.dist-info/entry_points.txt
oh_my_ralph-0.4.0.dist-info/top_level.txt
oh_my_ralph-0.4.0.dist-info/RECORD
