Metadata-Version: 2.4
Name: oh-my-ralph
Version: 0.4.0
Summary: An opinionated orchestrator for Ralph Wiggum loops
Home-page: https://github.com/vivganes/oh-my-ralph
Author: vivganes
License: MIT License
Project-URL: Homepage, https://github.com/vivganes/oh-my-ralph
Project-URL: Repository, https://github.com/vivganes/oh-my-ralph
Classifier: Programming Language :: Python :: 3
Classifier: License :: OSI Approved :: MIT License
Classifier: Operating System :: OS Independent
Requires-Python: >=3.10
License-File: LICENSE
Dynamic: home-page
Dynamic: license-file
Dynamic: requires-python
